epsexec.py
Enhanced_PsExec-0.6.8.dist-info/LICENSE.txt
Enhanced_PsExec-0.6.8.dist-info/METADATA
Enhanced_PsExec-0.6.8.dist-info/WHEEL
Enhanced_PsExec-0.6.8.dist-info/top_level.txt
Enhanced_PsExec-0.6.8.dist-info/RECORD
