Metadata-Version: 2.1
Name: Enhanced-PsExec
Version: 0.6.8
Summary: Perform miscellaneous operations on A remote computer with Enhanced PsExec
Home-page: https://github.com/orishamir/
Author: Ori Shamir
Author-email: Epsexecnoreply@gmail.com
License: UNKNOWN
Platform: UNKNOWN
Classifier: Programming Language :: Python :: 3.7
Classifier: Development Status :: 4 - Beta
Classifier: License :: OSI Approved :: MIT License
Classifier: Natural Language :: English
Classifier: Topic :: System :: Systems Administration
Classifier: Operating System :: Microsoft :: Windows
Requires-Dist: colorama
